README.md
setup.py
ImageRecogNeuralNet/__init__.py
ImageRecogNeuralNet.egg-info/PKG-INFO
ImageRecogNeuralNet.egg-info/SOURCES.txt
ImageRecogNeuralNet.egg-info/dependency_links.txt
ImageRecogNeuralNet.egg-info/entry_points.txt
ImageRecogNeuralNet.egg-info/requires.txt
ImageRecogNeuralNet.egg-info/top_level.txt